sig_scaffold/__init__.py
sig_scaffold/sig_scaffold.py
sigscaffold-0.1.0.dist-info/licenses/LICENSE
sigscaffold-0.1.0.dist-info/METADATA
sigscaffold-0.1.0.dist-info/WHEEL
sigscaffold-0.1.0.dist-info/top_level.txt
sigscaffold-0.1.0.dist-info/RECORD
