Metadata-Version: 2.4
Name: SigScaffold
Version: 0.1.0
Summary: A tool to derive parameter information from Python functions and classes for contract generation.
Author: Jake
Requires-Python: >=3.8
License-File: LICENSE
Dynamic: license-file
